skduplo
