Metadata-Version: 2.1
Name: skduplo
Version: 0.1.1
Summary: Sci-kit learn tools for machine learning pipelines
Home-page: http://getting-data-science-done.com
Author: John Hawkins
Author-email: johnc@getting-data-science-done.com
License: MIT
Project-URL: Documentation, http://scikit-duplo.readthedocs.io
Project-URL: Source, https://github.com/getting-data-science-done/scikit-duplo
Project-URL: Tracker, https://github.com/getting-data-science-done/scikit-duplo/issues
License-File: LICENSE
